README.txt
setup.py
Products/__init__.py
Products.Undoer.egg-info/PKG-INFO
Products.Undoer.egg-info/SOURCES.txt
Products.Undoer.egg-info/dependency_links.txt
Products.Undoer.egg-info/entry_points.txt
Products.Undoer.egg-info/namespace_packages.txt
Products.Undoer.egg-info/not-zip-safe
Products.Undoer.egg-info/requires.txt
Products.Undoer.egg-info/top_level.txt
Products/Undoer/__init__.py
Products/Undoer/changes.txt
Products/Undoer/readme.txt
Products/Undoer/version.txt
Products/Undoer/_darcs/index_invalid
Products/Undoer/_darcs/inventory
Products/Undoer/_darcs/tentative_pristine
Products/Undoer/_darcs/patches/20070302220303-422b6-1d68da8ccb66e644720a783ebf54d087733662b2.gz
Products/Undoer/_darcs/patches/20070302222054-422b6-6414f53823ecfd75d1c80eca620529c731d3732c.gz
Products/Undoer/_darcs/patches/20070302222320-422b6-74563599b6b958504c732290b8f09751648870ff.gz
Products/Undoer/_darcs/patches/20120124122650-422b6-0ddf56bcb9ccc7f85ecb0f4952faa613d47cf365.gz
Products/Undoer/_darcs/patches/20120124123504-422b6-5bec47fa89d2264f9e26c97c2d11fda972251271.gz
Products/Undoer/_darcs/patches/20120124123811-422b6-8218c457e49e5ac91a5b8f3da30c872d52b2d64c.gz
Products/Undoer/_darcs/patches/pending
Products/Undoer/_darcs/patches/pending.tentative
Products/Undoer/_darcs/prefs/author
Products/Undoer/_darcs/prefs/binaries
Products/Undoer/_darcs/prefs/boring
Products/Undoer/_darcs/prefs/defaultrepo
Products/Undoer/_darcs/prefs/motd
Products/Undoer/_darcs/prefs/repos
Products/Undoer/_darcs/pristine/__init__.py
Products/Undoer/_darcs/pristine/changes.txt
Products/Undoer/_darcs/pristine/readme.txt
Products/Undoer/_darcs/pristine/version.txt
Products/Undoer/_darcs/pristine/dtml/undo.dtml
Products/Undoer/dtml/undo.dtml