Metadata-Version: 1.0
Name: Products.Undoer
Version: 1.0.4
Summary: A tool that enables rolling back (undoing) changes to a Zope Application database based on date and time.
Home-page: http://www.nidelven-it.no/d
Author: Morten W. Petersen
Author-email: info@nidelven-it.no
License: ZPL 2.1
Keywords: zope plone silva zmi undo rollback database
Platform: UNKNOWN
Classifier: Programming Language :: Python
Classifier: Framework :: Zope2
Classifier: License :: OSI Approved :: Zope Public License
Classifier: Operating System :: OS Independent
Classifier: Topic :: Database
